[
{"id":"1","name":"Afghanistan","phoneCode":"93"},
{"id":"2","name":"Aland Islands","phoneCode":"+358-18"},
{"id":"3","name":"Albania","phoneCode":"355"},
{"id":"4","name":"Algeria","phoneCode":"213"},
{"id":"5","name":"American Samoa","phoneCode":"+1-684"},
{"id":"6","name":"Andorra","phoneCode":"376"},
{"id":"7","name":"Angola","phoneCode":"244"},
{"id":"8","name":"Anguilla","phoneCode":"+1-264"},
{"id":"9","name":"Antarctica","phoneCode":"672"},
{"id":"10","name":"Antigua And Barbuda","phoneCode":"+1-268"},
{"id":"11","name":"Argentina","phoneCode":"54"},
{"id":"12","name":"Armenia","phoneCode":"374"},
{"id":"13","name":"Aruba","phoneCode":"297"},
{"id":"14","name":"Australia","phoneCode":"61"},
{"id":"15","name":"Austria","phoneCode":"43"},
{"id":"16","name":"Azerbaijan","phoneCode":"994"},
{"id":"17","name":"Bahrain","phoneCode":"973"},
{"id":"18","name":"Bangladesh","phoneCode":"880"},
{"id":"19","name":"Barbados","phoneCode":"+1-246"},
{"id":"20","name":"Belarus","phoneCode":"375"},
{"id":"21","name":"Belgium","phoneCode":"32"},
{"id":"22","name":"Belize","phoneCode":"501"},
{"id":"23","name":"Benin","phoneCode":"229"},
{"id":"24","name":"Bermuda","phoneCode":"+1-441"},
{"id":"25","name":"Bhutan","phoneCode":"975"},
{"id":"26","name":"Bolivia","phoneCode":"591"},
{"id":"27","name":"Bonaire, Sint Eustatius and Saba","phoneCode":"599"},
{"id":"28","name":"Bosnia and Herzegovina","phoneCode":"387"},
{"id":"29","name":"Botswana","phoneCode":"267"},
{"id":"30","name":"Bouvet Island","phoneCode":"0055"},
{"id":"31","name":"Brazil","phoneCode":"55"},
{"id":"32","name":"British Indian Ocean Territory","phoneCode":"246"},
{"id":"33","name":"Brunei","phoneCode":"673"},
{"id":"34","name":"Bulgaria","phoneCode":"359"},
{"id":"35","name":"Burkina Faso","phoneCode":"226"},
{"id":"36","name":"Burundi","phoneCode":"257"},
{"id":"37","name":"Cambodia","phoneCode":"855"},
{"id":"38","name":"Cameroon","phoneCode":"237"},
{"id":"39","name":"Canada","phoneCode":"1"},
{"id":"40","name":"Cape Verde","phoneCode":"238"},
{"id":"41","name":"Cayman Islands","phoneCode":"+1-345"},
{"id":"42","name":"Central African Republic","phoneCode":"236"},
{"id":"43","name":"Chad","phoneCode":"235"},
{"id":"44","name":"Chile","phoneCode":"56"},
{"id":"45","name":"China","phoneCode":"86"},
{"id":"46","name":"Christmas Island","phoneCode":"61"},
{"id":"47","name":"Cocos (Keeling) Islands","phoneCode":"61"},
{"id":"48","name":"Colombia","phoneCode":"57"},
{"id":"49","name":"Comoros","phoneCode":"269"},
{"id":"50","name":"Congo","phoneCode":"242"},
{"id":"51","name":"Cook Islands","phoneCode":"682"},
{"id":"52","name":"Costa Rica","phoneCode":"506"},
{"id":"53","name":"Cote D\\'Ivoire (Ivory Coast)","phoneCode":"225"},
{"id":"54","name":"Croatia","phoneCode":"385"},
{"id":"55","name":"Cuba","phoneCode":"53"},
{"id":"56","name":"Curaçao","phoneCode":"599"},
{"id":"57","name":"Cyprus","phoneCode":"357"},
{"id":"58","name":"Czech Republic","phoneCode":"420"},
{"id":"59","name":"Democratic Republic of the Congo","phoneCode":"243"},
{"id":"60","name":"Denmark","phoneCode":"45"},
{"id":"61","name":"Djibouti","phoneCode":"253"},
{"id":"62","name":"Dominica","phoneCode":"+1-767"},
{"id":"63","name":"Dominican Republic","phoneCode":"+1-809 and 1-829"},
{"id":"64","name":"East Timor","phoneCode":"670"},
{"id":"65","name":"Ecuador","phoneCode":"593"},
{"id":"66","name":"Egypt","phoneCode":"20"},
{"id":"67","name":"El Salvador","phoneCode":"503"},
{"id":"68","name":"Equatorial Guinea","phoneCode":"240"},
{"id":"69","name":"Eritrea","phoneCode":"291"},
{"id":"70","name":"Estonia","phoneCode":"372"},
{"id":"71","name":"Ethiopia","phoneCode":"251"},
{"id":"72","name":"Falkland Islands","phoneCode":"500"},
{"id":"73","name":"Faroe Islands","phoneCode":"298"},
{"id":"74","name":"Fiji Islands","phoneCode":"679"},
{"id":"75","name":"Finland","phoneCode":"358"},
{"id":"76","name":"France","phoneCode":"33"},
{"id":"77","name":"French Guiana","phoneCode":"594"},
{"id":"78","name":"French Polynesia","phoneCode":"689"},
{"id":"79","name":"French Southern Territories","phoneCode":"262"},
{"id":"80","name":"Gabon","phoneCode":"241"},
{"id":"81","name":"Gambia The","phoneCode":"220"},
{"id":"82","name":"Georgia","phoneCode":"995"},
{"id":"83","name":"Germany","phoneCode":"49"},
{"id":"84","name":"Ghana","phoneCode":"233"},
{"id":"85","name":"Gibraltar","phoneCode":"350"},
{"id":"86","name":"Greece","phoneCode":"30"},
{"id":"87","name":"Greenland","phoneCode":"299"},
{"id":"88","name":"Grenada","phoneCode":"+1-473"},
{"id":"89","name":"Guadeloupe","phoneCode":"590"},
{"id":"90","name":"Guam","phoneCode":"+1-671"},
{"id":"91","name":"Guatemala","phoneCode":"502"},
{"id":"92","name":"Guernsey and Alderney","phoneCode":"+44-1481"},
{"id":"93","name":"Guinea","phoneCode":"224"},
{"id":"94","name":"Guinea-Bissau","phoneCode":"245"},
{"id":"95","name":"Guyana","phoneCode":"592"},
{"id":"96","name":"Haiti","phoneCode":"509"},
{"id":"97","name":"Heard Island and McDonald Islands","phoneCode":"672"},
{"id":"98","name":"Honduras","phoneCode":"504"},
{"id":"99","name":"Hong Kong S.A.R.","phoneCode":"852"},
{"id":"100","name":"Hungary","phoneCode":"36"},
{"id":"101","name":"Iceland","phoneCode":"354"},
{"id":"102","name":"India","phoneCode":"91"},
{"id":"103","name":"Indonesia","phoneCode":"62"},
{"id":"104","name":"Iran","phoneCode":"98"},
{"id":"105","name":"Iraq","phoneCode":"964"},
{"id":"106","name":"Ireland","phoneCode":"353"},
{"id":"107","name":"Israel","phoneCode":"972"},
{"id":"108","name":"Italy","phoneCode":"39"},
{"id":"109","name":"Jamaica","phoneCode":"+1-876"},
{"id":"110","name":"Japan","phoneCode":"81"},
{"id":"111","name":"Jersey","phoneCode":"+44-1534"},
{"id":"112","name":"Jordan","phoneCode":"962"},
{"id":"113","name":"Kazakhstan","phoneCode":"7"},
{"id":"114","name":"Kenya","phoneCode":"254"},
{"id":"115","name":"Kiribati","phoneCode":"686"},
{"id":"116","name":"Kosovo","phoneCode":"383"},
{"id":"117","name":"Kuwait","phoneCode":"965"},
{"id":"118","name":"Kyrgyzstan","phoneCode":"996"},
{"id":"119","name":"Laos","phoneCode":"856"},
{"id":"120","name":"Latvia","phoneCode":"371"},
{"id":"121","name":"Lebanon","phoneCode":"961"},
{"id":"122","name":"Lesotho","phoneCode":"266"},
{"id":"123","name":"Liberia","phoneCode":"231"},
{"id":"124","name":"Libya","phoneCode":"218"},
{"id":"125","name":"Liechtenstein","phoneCode":"423"},
{"id":"126","name":"Lithuania","phoneCode":"370"},
{"id":"127","name":"Luxembourg","phoneCode":"352"},
{"id":"128","name":"Macau S.A.R.","phoneCode":"853"},
{"id":"129","name":"Madagascar","phoneCode":"261"},
{"id":"130","name":"Malawi","phoneCode":"265"},
{"id":"131","name":"Malaysia","phoneCode":"60"},
{"id":"132","name":"Maldives","phoneCode":"960"},
{"id":"133","name":"Mali","phoneCode":"223"},
{"id":"134","name":"Malta","phoneCode":"356"},
{"id":"135","name":"Man (Isle of)","phoneCode":"+44-1624"},
{"id":"136","name":"Marshall Islands","phoneCode":"692"},
{"id":"137","name":"Martinique","phoneCode":"596"},
{"id":"138","name":"Mauritania","phoneCode":"222"},
{"id":"139","name":"Mauritius","phoneCode":"230"},
{"id":"140","name":"Mayotte","phoneCode":"262"},
{"id":"141","name":"Mexico","phoneCode":"52"},
{"id":"142","name":"Micronesia","phoneCode":"691"},
{"id":"143","name":"Moldova","phoneCode":"373"},
{"id":"144","name":"Monaco","phoneCode":"377"},
{"id":"145","name":"Mongolia","phoneCode":"976"},
{"id":"146","name":"Montenegro","phoneCode":"382"},
{"id":"147","name":"Montserrat","phoneCode":"+1-664"},
{"id":"148","name":"Morocco","phoneCode":"212"},
{"id":"149","name":"Mozambique","phoneCode":"258"},
{"id":"150","name":"Myanmar","phoneCode":"95"},
{"id":"151","name":"Namibia","phoneCode":"264"},
{"id":"152","name":"Nauru","phoneCode":"674"},
{"id":"153","name":"Nepal","phoneCode":"977"},
{"id":"154","name":"Netherlands","phoneCode":"31"},
{"id":"155","name":"New Caledonia","phoneCode":"687"},
{"id":"156","name":"New Zealand","phoneCode":"64"},
{"id":"157","name":"Nicaragua","phoneCode":"505"},
{"id":"158","name":"Niger","phoneCode":"227"},
{"id":"159","name":"Nigeria","phoneCode":"234"},
{"id":"160","name":"Niue","phoneCode":"683"},
{"id":"161","name":"Norfolk Island","phoneCode":"672"},
{"id":"162","name":"North Korea","phoneCode":"850"},
{"id":"163","name":"North Macedonia","phoneCode":"389"},
{"id":"164","name":"Northern Mariana Islands","phoneCode":"+1-670"},
{"id":"165","name":"Norway","phoneCode":"47"},
{"id":"166","name":"Oman","phoneCode":"968"},
{"id":"167","name":"Pakistan","phoneCode":"92"},
{"id":"168","name":"Palau","phoneCode":"680"},
{"id":"169","name":"Palestinian Territory Occupied","phoneCode":"970"},
{"id":"170","name":"Panama","phoneCode":"507"},
{"id":"171","name":"Papua new Guinea","phoneCode":"675"},
{"id":"172","name":"Paraguay","phoneCode":"595"},
{"id":"173","name":"Peru","phoneCode":"51"},
{"id":"174","name":"Philippines","phoneCode":"63"},
{"id":"175","name":"Pitcairn Island","phoneCode":"870"},
{"id":"176","name":"Poland","phoneCode":"48"},
{"id":"177","name":"Portugal","phoneCode":"351"},
{"id":"178","name":"Puerto Rico","phoneCode":"+1-787 and 1-939"},
{"id":"179","name":"Qatar","phoneCode":"974"},
{"id":"180","name":"Reunion","phoneCode":"262"},
{"id":"181","name":"Romania","phoneCode":"40"},
{"id":"182","name":"Russia","phoneCode":"7"},
{"id":"183","name":"Rwanda","phoneCode":"250"},
{"id":"184","name":"Saint Helena","phoneCode":"290"},
{"id":"185","name":"Saint Kitts And Nevis","phoneCode":"+1-869"},
{"id":"186","name":"Saint Lucia","phoneCode":"+1-758"},
{"id":"187","name":"Saint Pierre and Miquelon","phoneCode":"508"},
{"id":"188","name":"Saint Vincent And The Grenadines","phoneCode":"+1-784"},
{"id":"189","name":"Saint-Barthelemy","phoneCode":"590"},
{"id":"190","name":"Saint-Martin (French part)","phoneCode":"590"},
{"id":"191","name":"Samoa","phoneCode":"685"},
{"id":"192","name":"San Marino","phoneCode":"378"},
{"id":"193","name":"Sao Tome and Principe","phoneCode":"239"},
{"id":"194","name":"Saudi Arabia","phoneCode":"966"},
{"id":"195","name":"Senegal","phoneCode":"221"},
{"id":"196","name":"Serbia","phoneCode":"381"},
{"id":"197","name":"Seychelles","phoneCode":"248"},
{"id":"198","name":"Sierra Leone","phoneCode":"232"},
{"id":"199","name":"Singapore","phoneCode":"65"},
{"id":"200","name":"Sint Maarten (Dutch part)","phoneCode":"1721"},
{"id":"201","name":"Slovakia","phoneCode":"421"},
{"id":"202","name":"Slovenia","phoneCode":"386"},
{"id":"203","name":"Solomon Islands","phoneCode":"677"},
{"id":"204","name":"Somalia","phoneCode":"252"},
{"id":"205","name":"South Africa","phoneCode":"27"},
{"id":"206","name":"South Georgia","phoneCode":"500"},
{"id":"207","name":"South Korea","phoneCode":"82"},
{"id":"208","name":"South Sudan","phoneCode":"211"},
{"id":"209","name":"Spain","phoneCode":"34"},
{"id":"210","name":"Sri Lanka","phoneCode":"94"},
{"id":"211","name":"Sudan","phoneCode":"249"},
{"id":"212","name":"Suriname","phoneCode":"597"},
{"id":"213","name":"Svalbard And Jan Mayen Islands","phoneCode":"47"},
{"id":"214","name":"Swaziland","phoneCode":"268"},
{"id":"215","name":"Sweden","phoneCode":"46"},
{"id":"216","name":"Switzerland","phoneCode":"41"},
{"id":"217","name":"Syria","phoneCode":"963"},
{"id":"218","name":"Taiwan","phoneCode":"886"},
{"id":"219","name":"Tajikistan","phoneCode":"992"},
{"id":"220","name":"Tanzania","phoneCode":"255"},
{"id":"221","name":"Thailand","phoneCode":"66"},
{"id":"222","name":"The Bahamas","phoneCode":"+1-242"},
{"id":"223","name":"Togo","phoneCode":"228"},
{"id":"224","name":"Tokelau","phoneCode":"690"},
{"id":"225","name":"Tonga","phoneCode":"676"},
{"id":"226","name":"Trinidad And Tobago","phoneCode":"+1-868"},
{"id":"227","name":"Tunisia","phoneCode":"216"},
{"id":"228","name":"Turkey","phoneCode":"90"},
{"id":"229","name":"Turkmenistan","phoneCode":"993"},
{"id":"230","name":"Turks And Caicos Islands","phoneCode":"+1-649"},
{"id":"231","name":"Tuvalu","phoneCode":"688"},
{"id":"232","name":"Uganda","phoneCode":"256"},
{"id":"233","name":"Ukraine","phoneCode":"380"},
{"id":"234","name":"United Arab Emirates","phoneCode":"971"},
{"id":"235","name":"United Kingdom","phoneCode":"44"},
{"id":"236","name":"United States","phoneCode":"1"},
{"id":"237","name":"United States Minor Outlying Islands","phoneCode":"1"},
{"id":"238","name":"Uruguay","phoneCode":"598"},
{"id":"239","name":"Uzbekistan","phoneCode":"998"},
{"id":"240","name":"Vanuatu","phoneCode":"678"},
{"id":"241","name":"Vatican City State (Holy See)","phoneCode":"379"},
{"id":"242","name":"Venezuela","phoneCode":"58"},
{"id":"243","name":"Vietnam","phoneCode":"84"},
{"id":"244","name":"Virgin Islands (British)","phoneCode":"+1-284"},
{"id":"245","name":"Virgin Islands (US)","phoneCode":"+1-340"},
{"id":"246","name":"Wallis And Futuna Islands","phoneCode":"681"},
{"id":"247","name":"Western Sahara","phoneCode":"212"},
{"id":"248","name":"Yemen","phoneCode":"967"},
{"id":"249","name":"Zambia","phoneCode":"260"},
{"id":"250","name":"Zimbabwe","phoneCode":"263"}
]